apns2/__init__.py
apns2/client.py
apns2/credentials.py
apns2/errors.py
apns2/payload.py
apns2-0.7.1.dist-info/LICENSE
apns2-0.7.1.dist-info/METADATA
apns2-0.7.1.dist-info/WHEEL
apns2-0.7.1.dist-info/top_level.txt
apns2-0.7.1.dist-info/RECORD
